Workbook

Sheet Chart of Accounts
A1: NexaNet Communications Chart of Accounts (Reference)
A2: CONFIDENTIAL Finance-Archive\staging Internal use only. Company Reg. 915501328 NEXA House, Victoria Island, Lagos
A4: Account Code | B4: Account Name | C4: Account Type
A5: 4000 | B5: Revenue Enterprise Contracts | C5: Revenue
A6: 4010 | B6: Revenue Consumer Broadband | C6: Revenue
A7: 5000 | B7: Cost of Sales Network Operations | C7: Expense
A8: 6000 | B8: Payroll & Employee Costs | C8: Expense
A9: 6100 | B9: Professional & Legal Fees | C9: Expense
A10: 6200 | B10: Vendor & Contractor Payments | C10: Expense
A11: 6300 | B11: Facilities & Utilities | C11: Expense
A12: 7000 | B12: Capital Expenditure Network | C12: Asset
A13: 7100 | B13: Capital Expenditure Property | C13: Asset
A14: 1000 | B14: Bank Operating Account (GBP) | C14: Asset
A15: 1010 | B15: Bank Operating Account (NGN) | C15: Asset
... A17: 2100 | B17: Accounts Receivable | C17: Asset

Sheet GL Transactions Q2
A1: Consolidated General Ledger Export — Q2 2026 (Apr–Jun)
A2: CONFIDENTIAL — Finance-Archive\staging — Internal use only. Company Reg. 915501328 — NEXA House, Victoria Island, Lagos
A4: Txn ID | B4: Date | C4: Account Code | D4: Account Name | E4: Cost Centre | F4: Description | G4: Counterparty / Reference | H4: Debit (GBP) | I4: Credit (GBP) | J4: Entered By
A5: GL-Q2-00114 | B5: 2026-04-03 | C5: 6000 | D5: Payroll & Employee Costs | E5: HR-Records\Payroll | F5: April payroll run — all departments | G5: See payroll_extract_july.xlsx for July equivalent | H5: 612480 | I5: 0 | J5: Sarah Whitfield
A6: GL-Q2-00115 | B6: 2026-04-03 | C6: 1000 | D6: Bank — Operating Account (GBP) | E6: Finance | F6: April payroll disbursement | G6: BACS batch NX-PAY-2026-04 | H6: 0 | I6: 612480 | J6: Sarah Whitfield
A7: GL-Q2-00128 | B7: 2026-04-11 | C7: 6200 | D7: Vendor & Contractor Payments | E7: Legal\Contracts | F7: Ridgeline Fibre Contractors — civil works Q2 milestone 1 | G7: PO NX-PO-2026-0512 / NDA NX-VND-NDA-2026-0146 | H7: 186000 | I7: 0 | J7: Chidi Eze
A8: GL-Q2-00129 | B8: 2026-04-11 | C8: 1000 | D8: Bank — Operating Account (GBP) | E8: Finance | F8: Payment to Ridgeline Fibre Contractors Ltd | G8: Bank transfer ref RFC-Q2-01 | H8: 0 | I8: 186000 | J8: Michael Bamgbose
A9: GL-Q2-00142 | B9: 2026-04-22 | C9: 4000 | D9: Revenue — Enterprise Contracts | E9: Sales\AccountPlans | F9: Westgate Financial Services — Q2 service fee | G9: Account NX-ACC-3428 | H9: 0 | I9: 89000 | J9: Ifeoma Chukwu
A10: GL-Q2-00143 | B10: 2026-04-22 | C10: 2100 | D10: Accounts Receivable | E10: Sales\AccountPlans | F10: Westgate Financial Services — Q2 invoice raised | G10: Account NX-ACC-3428 | H10: 89000 | I10: 0 | J10: Ifeoma Chukwu
A11: GL-Q2-00156 | B11: 2026-05-02 | C11: 6200 | D11: Vendor & Contractor Payments | E11: Engineering\CoreNetwork | F11: Ericsson — core equipment service contract | G11: See invoice_vendor_ericsson_svc.pdf | H11: 36356 | I11: 0 | J11: Michael Bamgbose
A12: GL-Q2-00157 | B12: 2026-05-02 | C12: 1000 | D12: Bank — Operating Account (GBP) | E12: Finance | F12: Payment to Ericsson Nigeria Ltd | G12: Bank transfer ref ERI-Q2-04 | H12: 0 | I12: 36356 | J12: Michael Bamgbose
A13: GL-Q2-00168 | B13: 2026-05-09 | C13: 6000 | D13: Payroll & Employee Costs | E13: HR-Records\Payroll | F13: May payroll run — all departments | G13: See payroll_extract_july.xlsx for July equivalent | H13: 618750 | I13: 0 | J13: Sarah Whitfield
A14: GL-Q2-00169 | B14: 2026-05-09 | C14: 1000 | D14: Bank — Operating Account (GBP) | E14: Finance | F14: May payroll disbursement | G14: BACS batch NX-PAY-2026-05 | H14: 0 | I14: 618750 | J14: Sarah Whitfield
A15: GL-Q2-00174 | B15: 2026-05-14 | C15: 4000 | D15: Revenue — Enterprise Contracts | E15: Sales\AccountPlans | F15: Northbank Insurance Group — Q2 service fee | G15: Account NX-ACC-3369 | H15: 0 | I15: 66750 | J15: Ifeoma Chukwu
A16: GL-Q2-00175 | B16: 2026-05-14 | C16: 2100 | D16: Accounts Receivable | E16: Sales\AccountPlans | F16: Northbank Insurance Group — Q2 invoice raised | G16: Account NX-ACC-3369 | H16: 66750 | I16: 0 | J16: Ifeoma Chukwu
... A30: GL-Q2-00241 | B30: 2026-06-25 | C30: 1000 | D30: Bank — Operating Account (GBP) | E30: Finance | F30: Payment to Ridgeline Fibre Contractors Ltd | G30: Bank transfer ref RFC-Q2-02 | H30: 0 | I30: 154000 | J30: Michael Bamgbose
F31: TOTAL | H31: =SUM(H5:H30) -> 2905286 | I31: =SUM(I5:I30) -> 2905286

Sheet Trial Balance Summary
A1: Trial Balance Summary — Q2 2026 (by Account)
A2: CONFIDENTIAL — Finance-Archive\staging — Internal use only. Company Reg. 915501328 — NEXA House, Victoria Island, Lagos
A4: Account Code | B4: Account Name | C4: Total Debit (GBP) | D4: Total Credit (GBP)
A5: 4000 | B5: Revenue — Enterprise Contracts | C5: =SUMIF('GL Transactions Q2'!$C$5:$C$30,A5,'GL Transactions Q2'!$H$5:$H$30) -> 0 | D5: =SUMIF('GL Transactions Q2'!$C$5:$C$30,A5,'GL Transactions Q2'!$I$5:$I$30) -> 224500
A6: 4010 | B6: Revenue — Consumer Broadband | C6: =SUMIF('GL Transactions Q2'!$C$5:$C$30,A6,'GL Transactions Q2'!$H$5:$H$30) -> 0 | D6: =SUMIF('GL Transactions Q2'!$C$5:$C$30,A6,'GL Transactions Q2'!$I$5:$I$30) -> 0
A7: 5000 | B7: Cost of Sales — Network Operations | C7: =SUMIF('GL Transactions Q2'!$C$5:$C$30,A7,'GL Transactions Q2'!$H$5:$H$30) -> 0 | D7: =SUMIF('GL Transactions Q2'!$C$5:$C$30,A7,'GL Transactions Q2'!$I$5:$I$30) -> 0
A8: 6000 | B8: Payroll & Employee Costs | C8: =SUMIF('GL Transactions Q2'!$C$5:$C$30,A8,'GL Transactions Q2'!$H$5:$H$30) -> 1840430 | D8: =SUMIF('GL Transactions Q2'!$C$5:$C$30,A8,'GL Transactions Q2'!$I$5:$I$30) -> 0
A9: 6100 | B9: Professional & Legal Fees | C9: =SUMIF('GL Transactions Q2'!$C$5:$C$30,A9,'GL Transactions Q2'!$H$5:$H$30) -> 18500 | D9: =SUMIF('GL Transactions Q2'!$C$5:$C$30,A9,'GL Transactions Q2'!$I$5:$I$30) -> 0
A10: 6200 | B10: Vendor & Contractor Payments | C10: =SUMIF('GL Transactions Q2'!$C$5:$C$30,A10,'GL Transactions Q2'!$H$5:$H$30) -> 376356 | D10: =SUMIF('GL Transactions Q2'!$C$5:$C$30,A10,'GL Transactions Q2'!$I$5:$I$30) -> 0
A11: 6300 | B11: Facilities & Utilities | C11: =SUMIF('GL Transactions Q2'!$C$5:$C$30,A11,'GL Transactions Q2'!$H$5:$H$30) -> 42500 | D11: =SUMIF('GL Transactions Q2'!$C$5:$C$30,A11,'GL Transactions Q2'!$I$5:$I$30) -> 0
A12: 7000 | B12: Capital Expenditure — Network | C12: =SUMIF('GL Transactions Q2'!$C$5:$C$30,A12,'GL Transactions Q2'!$H$5:$H$30) -> 340000 | D12: =SUMIF('GL Transactions Q2'!$C$5:$C$30,A12,'GL Transactions Q2'!$I$5:$I$30) -> 0
A13: 7100 | B13: Capital Expenditure — Property | C13: =SUMIF('GL Transactions Q2'!$C$5:$C$30,A13,'GL Transactions Q2'!$H$5:$H$30) -> 63000 | D13: =SUMIF('GL Transactions Q2'!$C$5:$C$30,A13,'GL Transactions Q2'!$I$5:$I$30) -> 0
A14: 1000 | B14: Bank — Operating Account (GBP) | C14: =SUMIF('GL Transactions Q2'!$C$5:$C$30,A14,'GL Transactions Q2'!$H$5:$H$30) -> 0 | D14: =SUMIF('GL Transactions Q2'!$C$5:$C$30,A14,'GL Transactions Q2'!$I$5:$I$30) -> 2277786
A15: 1010 | B15: Bank — Operating Account (NGN) | C15: =SUMIF('GL Transactions Q2'!$C$5:$C$30,A15,'GL Transactions Q2'!$H$5:$H$30) -> 0 | D15: =SUMIF('GL Transactions Q2'!$C$5:$C$30,A15,'GL Transactions Q2'!$I$5:$I$30) -> 0
A16: 2000 | B16: Accounts Payable | C16: =SUMIF('GL Transactions Q2'!$C$5:$C$30,A16,'GL Transactions Q2'!$H$5:$H$30) -> 0 | D16: =SUMIF('GL Transactions Q2'!$C$5:$C$30,A16,'GL Transactions Q2'!$I$5:$I$30) -> 403000
A17: 2100 | B17: Accounts Receivable | C17: =SUMIF('GL Transactions Q2'!$C$5:$C$30,A17,'GL Transactions Q2'!$H$5:$H$30) -> 224500 | D17: =SUMIF('GL Transactions Q2'!$C$5:$C$30,A17,'GL Transactions Q2'!$I$5:$I$30) -> 0
B18: TOTAL | C18: =SUM(C5:C17) -> 2905286 | D18: =SUM(D5:D17) -> 2905286
B20: Balance Check (Debit − Credit) | C20: =C18-D18 -> 0
